feediverse.py
feediverse-0.4.1.dist-info/LICENSE
feediverse-0.4.1.dist-info/METADATA
feediverse-0.4.1.dist-info/WHEEL
feediverse-0.4.1.dist-info/entry_points.txt
feediverse-0.4.1.dist-info/RECORD
