Metadata-Version: 2.1
Name: feediverse
Version: 0.4.1
Summary: Connect an RSS Feed to Mastodon
License: MIT
Author: Ed Summers
Author-email: ehs@pobox.com
Requires-Python: >=3.9,<4.0
Classifier: License :: OSI Approved :: MIT License
Classifier: Programming Language :: Python :: 3
Classifier: Programming Language :: Python :: 3.9
Classifier: Programming Language :: Python :: 3.10
Classifier: Programming Language :: Python :: 3.11
Classifier: Programming Language :: Python :: 3.12
Requires-Dist: beautifulsoup4 (>=4.12.3,<5.0.0)
Requires-Dist: feedparser (>=6.0.11,<7.0.0)
Requires-Dist: mastodon-py (>=1.8.1,<2.0.0)
Requires-Dist: python-dateutil (>=2.9.0.post0,<3.0.0)
Requires-Dist: pyyaml (>=6.0.1,<7.0.0)
Requires-Dist: requests (>=2.32.2,<3.0.0)
